pyramid_swagger_router/__init__.py
pyramid_swagger_router/asthandler.py
pyramid_swagger_router/cmd.py
pyramid_swagger_router/codegen.py
pyramid_swagger_router/driver.py
pyramid_swagger_router/resolver.py
pyramid_swagger_router/tests/__init__.py
pyramid_swagger_router/tests/test_asthandler.py
pyramid_swagger_router-0.1.3.dist-info/DESCRIPTION.rst
pyramid_swagger_router-0.1.3.dist-info/entry_points.txt
pyramid_swagger_router-0.1.3.dist-info/METADATA
pyramid_swagger_router-0.1.3.dist-info/metadata.json
pyramid_swagger_router-0.1.3.dist-info/RECORD
pyramid_swagger_router-0.1.3.dist-info/top_level.txt
pyramid_swagger_router-0.1.3.dist-info/WHEEL
