Metadata-Version: 2.0
Name: pyramid-swagger-router
Version: 0.1.3
Summary: view's code generation from a swagger's definition file.
Home-page: https://github.com/podhmo/pyramid-swagger-router
Author: podhmo
Author-email: ababjam61@gmail.com
License: UNKNOWN
Keywords: swagger,pyramid,code-generation,view,router
Platform: UNKNOWN
Classifier: Programming Language :: Python
Classifier: Programming Language :: Python :: Implementation :: CPython
Requires-Dist: magicalimport
Requires-Dist: dictknife[load]
Requires-Dist: prestring
Requires-Dist: redbaron
Provides-Extra: docs
Provides-Extra: testing
